mridatapy/__init__.py
mridatapy/data/__init__.py
mridatapy/data/mridata.py
mridatapy/data/subsample.py
mridatapy/metrics/__init__.py
mridatapy/metrics/evaluate.py
mridatapy/utils/__init__.py
mridatapy/utils/coil_combine.py
mridatapy/utils/transforms.py
mridataPy-0.0.6.dist-info/LICENSE
mridataPy-0.0.6.dist-info/METADATA
mridataPy-0.0.6.dist-info/WHEEL
mridataPy-0.0.6.dist-info/top_level.txt
mridataPy-0.0.6.dist-info/RECORD
